setup.py
checkmate/__init__.py
checkmate/__main__.py
checkmate.egg-info/PKG-INFO
checkmate.egg-info/SOURCES.txt
checkmate.egg-info/dependency_links.txt
checkmate.egg-info/entry_points.txt
checkmate.egg-info/not-zip-safe
checkmate.egg-info/requires.txt
checkmate.egg-info/top_level.txt
checkmate/contrib/__init__.py
checkmate/contrib/plugins/__init__.py
checkmate/contrib/plugins/git/__init__.py
checkmate/contrib/plugins/git/helpers.py
checkmate/contrib/plugins/git/models.py
checkmate/contrib/plugins/git/setup.py
checkmate/contrib/plugins/git/commands/__init__.py
checkmate/contrib/plugins/git/commands/analyze.py
checkmate/contrib/plugins/git/commands/base.py
checkmate/contrib/plugins/git/commands/diff.py
checkmate/contrib/plugins/git/commands/update_stats.py
checkmate/contrib/plugins/git/hooks/__init__.py
checkmate/contrib/plugins/git/hooks/project.py
checkmate/contrib/plugins/git/lib/__init__.py
checkmate/contrib/plugins/git/lib/repository.py
checkmate/contrib/plugins/git/lib/repository_pygit2.py
checkmate/contrib/plugins/git/test/__init__.py
checkmate/contrib/plugins/git/test/helpers.py
checkmate/contrib/plugins/git/test/analysis/__init__.py
checkmate/contrib/plugins/git/test/analysis/test_analysis.py
checkmate/contrib/plugins/git/test/analysis/test_diffing.py
checkmate/contrib/plugins/git/test/git/__init__.py
checkmate/contrib/plugins/git/test/git/test_git.py
checkmate/contrib/plugins/git/test/lib/__init__.py
checkmate/contrib/plugins/git/test/lib/test_repository.py
checkmate/contrib/plugins/github/__init__.py
checkmate/contrib/plugins/github/models.py
checkmate/contrib/plugins/github/setup.py
checkmate/contrib/plugins/github/commands/__init__.py
checkmate/contrib/plugins/github/commands/analyze_pull_requests.py
checkmate/contrib/plugins/javascript/__init__.py
checkmate/contrib/plugins/javascript/jshint/__init__.py
checkmate/contrib/plugins/javascript/jshint/analyzer.py
checkmate/contrib/plugins/javascript/jshint/issues_data.py
checkmate/contrib/plugins/javascript/jshint/setup.py
checkmate/contrib/plugins/python/__init__.py
checkmate/contrib/plugins/python/metrics/__init__.py
checkmate/contrib/plugins/python/metrics/analyzer.py
checkmate/contrib/plugins/python/metrics/issues_data.py
