Metadata-Version: 1.0
Name: checkmate
Version: 0.2.0
Summary: A meta-code checker written in Python.
Home-page: https://github.com/quantifiedcode/checkmate
Author: Andreas Dewes - QuantifiedCode UG (haftungsbeschränkt)
Author-email: andreas@quantifiedcode.com
License: MIT
Platform: UNKNOWN
